setup.py
flask_thumbor/__init__.py
flask_thumbor/thumbor.py
flask_thumbor/version.py
flask_thumbor.egg-info/PKG-INFO
flask_thumbor.egg-info/SOURCES.txt
flask_thumbor.egg-info/dependency_links.txt
flask_thumbor.egg-info/entry_points.txt
flask_thumbor.egg-info/requires.txt
flask_thumbor.egg-info/top_level.txt
tests/__init__.py
tests/base.py
tests/test_version.py