Metadata-Version: 1.1
Name: flask-thumbor
Version: 0.1.0
Summary: Flask utilities to use thumbor images. 
Home-page: https://github.com/thumby/flask-thumbor
Author: Thumby
Author-email: dev@thumby.io
License: MIT
Keywords: flask python thumbor images responsive
Platform: UNKNOWN
Classifier: Development Status :: 4 - Beta
Classifier: Intended Audience :: Developers
Classifier: License :: OSI Approved :: MIT License
Classifier: Natural Language :: English
Classifier: Operating System :: Unix
Classifier: Programming Language :: Python :: 2.7
Classifier: Programming Language :: Python :: 3.4
Classifier: Programming Language :: Python :: Implementation :: PyPy
Classifier: Operating System :: OS Independent
